trinsic_okapi-1.6.1.data/data/libs/linux/libokapi.so
trinsic_okapi-1.6.1.data/data/libs/linux-aarch64/libokapi.so
trinsic_okapi-1.6.1.data/data/libs/linux-armv7/libokapi.so
trinsic_okapi-1.6.1.data/data/libs/macos/libokapi.dylib
trinsic_okapi-1.6.1.data/data/libs/windows/okapi.dll
trinsicokapi/__init__.py
trinsicokapi/__main__.py
trinsicokapi/didcomm.py
trinsicokapi/didkey.py
trinsicokapi/hashing.py
trinsicokapi/ldproofs.py
trinsicokapi/metadata.py
trinsicokapi/oberon.py
trinsicokapi/okapi_utils.py
trinsicokapi/wrapper.py
trinsicokapi/libs/linux/libokapi.so
trinsicokapi/libs/linux-aarch64/libokapi.so
trinsicokapi/libs/linux-armv7/libokapi.so
trinsicokapi/libs/macos/libokapi.dylib
trinsicokapi/libs/windows/okapi.dll
trinsicokapi/proto/__init__.py
trinsicokapi/proto/okapi/__init__.py
trinsicokapi/proto/okapi/examples/__init__.py
trinsicokapi/proto/okapi/examples/v1/__init__.py
trinsicokapi/proto/okapi/hashing/__init__.py
trinsicokapi/proto/okapi/hashing/v1/__init__.py
trinsicokapi/proto/okapi/keys/__init__.py
trinsicokapi/proto/okapi/keys/v1/__init__.py
trinsicokapi/proto/okapi/metadata/__init__.py
trinsicokapi/proto/okapi/proofs/__init__.py
trinsicokapi/proto/okapi/proofs/v1/__init__.py
trinsicokapi/proto/okapi/security/__init__.py
trinsicokapi/proto/okapi/security/v1/__init__.py
trinsicokapi/proto/okapi/transport/__init__.py
trinsicokapi/proto/okapi/transport/v1/__init__.py
trinsicokapi/proto/pbmse/__init__.py
trinsicokapi/proto/pbmse/v1/__init__.py
trinsic_okapi-1.6.1.dist-info/METADATA
trinsic_okapi-1.6.1.dist-info/WHEEL
trinsic_okapi-1.6.1.dist-info/top_level.txt
trinsic_okapi-1.6.1.dist-info/RECORD
