Metadata-Version: 2.1
Name: trinsic-okapi
Version: 1.6.1
Summary: Trinsic okapi SDK bindings
Home-page: https://github.com/trinsic-id/okapi/python
Author: Scott Phillips
Author-email: scott.phillips@trinsic.id
Project-URL: Bug Tracker, https://github.com/trinsic-id/okapi/issues
Classifier: Programming Language :: Python :: 3
Classifier: License :: OSI Approved :: Apache Software License
Classifier: Operating System :: OS Independent
Requires-Python: >=3.7
Requires-Dist: protobuf (>=3.17.3)
Requires-Dist: betterproto (>=2.0.0b4)
Requires-Dist: requests (>=2.27.1)
